data/tickers.json
unusualvolume/__init__.py
unusualvolume/cli.py
unusualvolume/scanner.py
unusualvolume/tickers.py
unusualvolume-0.1.2.dist-info/entry_points.txt
unusualvolume-0.1.2.dist-info/LICENSE.md
unusualvolume-0.1.2.dist-info/WHEEL
unusualvolume-0.1.2.dist-info/METADATA
unusualvolume-0.1.2.dist-info/RECORD
